df_extract/__init__.py
df_extract/base.py
df_extract/csv.py
df_extract/docx.py
df_extract/extract_util.py
df_extract/image.py
df_extract/pdf.py
df_extract/pptx.py
df_extract/utils.py
df_extract-0.0.2.1.dist-info/LICENSE.txt
df_extract-0.0.2.1.dist-info/METADATA
df_extract-0.0.2.1.dist-info/WHEEL
df_extract-0.0.2.1.dist-info/top_level.txt
df_extract-0.0.2.1.dist-info/RECORD
