Metadata-Version: 2.1
Name: df-extract
Version: 0.0.2.1
Summary: DecisionFacts Extraction Library extracts content from PDF, PPTX, Docx, png, jpg., and convert as structured JSON data.
Home-page: https://github.com/decisionfacts/df-extract
Download-URL: https://github.com/decisionfacts/df-extract.git
Author: Syed
Author-email: syed@decisionfacts.io
Maintainer: DecisionFacts
Maintainer-email: info@decisionfacts.io
License: Apache License 2.0
Keywords: df extract content pdf pptx ppt docx doc png jpg jpeg
License-File: LICENSE.txt
Requires-Dist: aiocsv ==1.2.4
Requires-Dist: aiofiles ==23.1.0
Requires-Dist: aiopath ==0.6.11
Requires-Dist: easyocr ==1.7.0
Requires-Dist: Pillow ==9.5.0
Requires-Dist: PyMuPDF ==1.22.5
Requires-Dist: python-pptx ==0.6.21
Requires-Dist: python-docx ==0.8.11
